brother_ql_web/__init__.py
brother_ql_web/__main__.py
brother_ql_web/cli.py
brother_ql_web/configuration.py
brother_ql_web/font_helpers.py
brother_ql_web/labels.py
brother_ql_web/utils.py
brother_ql_web/web.py
brother_ql_web/static/css/bootstrap-icons.min.css
brother_ql_web/static/css/bootstrap.min.css
brother_ql_web/static/css/bootstrap.min.css.map
brother_ql_web/static/css/custom.css
brother_ql_web/static/fonts/bootstrap-icons.woff
brother_ql_web/static/fonts/bootstrap-icons.woff2
brother_ql_web/static/js/bootstrap.min.js
brother_ql_web/static/js/bootstrap.min.js.map
brother_ql_web/views/base.jinja2
brother_ql_web/views/labeldesigner.jinja2
brother_ql_web-0.5.0.dist-info/LICENSE
brother_ql_web-0.5.0.dist-info/METADATA
brother_ql_web-0.5.0.dist-info/WHEEL
brother_ql_web-0.5.0.dist-info/entry_points.txt
brother_ql_web-0.5.0.dist-info/top_level.txt
brother_ql_web-0.5.0.dist-info/RECORD
