Metadata-Version: 2.1
Name: brother-ql-web
Version: 0.5.0
Summary: Simple label designer API and web API for Brother QL label printers
Author: Philipp Klaus
Maintainer: FriedrichFröbel
License: GPL-3.0-only
Project-URL: Homepage, https://github.com/FriedrichFroebel/brother_ql_web/
Project-URL: Repository, https://github.com/FriedrichFroebel/brother_ql_web/
Project-URL: Issues, https://github.com/FriedrichFroebel/brother_ql_web//issues
Project-URL: Changelog, https://github.com/FriedrichFroebel/brother_ql_web/blob/master/CHANGELOG.md
Keywords: brother,brother_ql,label,printer
Classifier: Development Status :: 4 - Beta
Classifier: Environment :: Web Environment
Classifier: Framework :: Bottle
Classifier: Intended Audience :: Developers
Classifier: Intended Audience :: End Users/Desktop
Classifier: License :: OSI Approved :: GNU General Public License v3 (GPLv3)
Classifier: Operating System :: OS Independent
Classifier: Programming Language :: Python
Classifier: Programming Language :: Python :: 3
Classifier: Programming Language :: Python :: 3 :: Only
Classifier: Topic :: Multimedia :: Graphics
Requires-Python: <4,>=3.9
License-File: LICENSE
Requires-Dist: brother_ql
Requires-Dist: bottle
Requires-Dist: jinja2
Requires-Dist: Pillow>=8
Provides-Extra: fontra
Requires-Dist: fontra>=0.5.2; extra == "fontra"
Provides-Extra: dev
Requires-Dist: black; extra == "dev"
Requires-Dist: codespell; extra == "dev"
Requires-Dist: flake8; extra == "dev"
Requires-Dist: pep8-naming; extra == "dev"
Requires-Dist: flake8-bugbear; extra == "dev"
Requires-Dist: requests; extra == "dev"
Provides-Extra: mypy
Requires-Dist: mypy; extra == "mypy"
Requires-Dist: types-Pillow; extra == "mypy"
Requires-Dist: types-requests; extra == "mypy"
